LICENSE.txt
MANIFEST.in
readme.rst
run_tests.py
setup.py
docs/Makefile
docs/source/_global.rst
docs/source/accessing_method_wrappers.rst
docs/source/appendix_II_what_has_been_new.rst
docs/source/appendix_I_parameters_reference.rst
docs/source/bulk_external_redecorating.rst
docs/source/call_chains.rst
docs/source/call_history_and_statistics.rst
docs/source/conf.py
docs/source/decorating_classes.rst
docs/source/dynamic_control_of_settings.rst
docs/source/further_examples_and_use_cases.rst
docs/source/index.rst
docs/source/indirect_values.rst
docs/source/installation.rst
docs/source/intro.rst
docs/source/parameters.rst
docs/source/quickstart.rst
docs/source/record_history_deco.rst
docs/source/retrieving_changing_defaults.rst
docs/source/using_loggers.rst
docs/source/what_log_calls_can_decorate.rst
docs/source/whats_new.rst
docs/source/writing_log_calls_aware_debug_messages.rst
docs/source/_static/Donate-AQUA.png
docs/source/_static/Donate-BLUE.png
docs/source/_static/Donate-ORANGE.png
docs/source/_static/Donate-YELLOW.png
docs/source/_static/blue.png
docs/source/_static/custom.css
docs/source/_templates/footer.html
docs/source/_templates/layout.html
log_calls/__init__.py
log_calls/deco_settings.py
log_calls/helpers.py
log_calls/log_calls.py
log_calls/proxy_descriptors.py
log_calls/record_history.py
log_calls/used_unused_kwds.py
log_calls/version.py
log_calls.egg-info/PKG-INFO
log_calls.egg-info/SOURCES.txt
log_calls.egg-info/dependency_links.txt
log_calls.egg-info/top_level.txt
tests/.log_calls
tests/__init__.py
tests/bad-settings.txt
tests/log_calls-settings.txt
tests/settings-with-NO_DECO.txt
tests/settings_with_NO_DECO.py
tests/some_module.py
tests/some_other_module.py
tests/test_deco_lambda_cant_deco_callables.py
tests/test_deco_settings.py
tests/test_decorate_module__deco_imported_class.py
tests/test_decorate_things_in_module.py
tests/test_double_func_deco.py
tests/test_get_own_log_calls_wrapper.py
tests/test_helpers.py
tests/test_log_calls.py
tests/test_log_calls__class_deco.py
tests/test_log_calls_as_record_history.py
tests/test_log_calls_log_methods.py
tests/test_log_calls_more.py
