Metadata-Version: 1.1
Name: log-calls
Version: 0.3.2
Summary: Debugging and profiling decorator for functions and classes that logs caller name(s), args+values, execution time, and more. Eliminates reams of boilerplate code.
Home-page: http://github.com/Twangist/log_calls
Author: Brian O'Neill
Author-email: twangist@gmail.com
License: MIT
Keywords: decorator debugging profiling logging function method class call caller stack recursion exploring learning teaching
Platform: UNKNOWN
Classifier: Development Status :: 5 - Production/Stable
Classifier: License :: OSI Approved :: MIT License
Classifier: Programming Language :: Python
Classifier: Programming Language :: Python :: 3
Classifier: Programming Language :: Python :: 3.3
Classifier: Programming Language :: Python :: 3.4
Classifier: Programming Language :: Python :: 3.5
Classifier: Programming Language :: Python :: 3.6
Classifier: Programming Language :: Python :: Implementation :: CPython
Classifier: Intended Audience :: Developers
Classifier: Operating System :: OS Independent
Classifier: Topic :: Software Development :: Libraries
Classifier: Topic :: Software Development :: Code Generators
Classifier: Topic :: Utilities
Classifier: Topic :: System :: Logging
